dptools/stopwatch/__init__.py
dptools_stopwatch-1.0.1.dist-info/METADATA
dptools_stopwatch-1.0.1.dist-info/WHEEL
dptools_stopwatch-1.0.1.dist-info/top_level.txt
dptools_stopwatch-1.0.1.dist-info/RECORD
